pyconify/__init__.py
pyconify/_cache.py
pyconify/api.py
pyconify/freedesktop.py
pyconify/iconify_types.py
pyconify/py.typed
pyconify-0.1.5.dist-info/METADATA
pyconify-0.1.5.dist-info/WHEEL
pyconify-0.1.5.dist-info/licenses/LICENSE
pyconify-0.1.5.dist-info/RECORD
